zipreport/__init__.py
zipreport-0.1.dist-info/LICENSE
zipreport-0.1.dist-info/METADATA
zipreport-0.1.dist-info/WHEEL
zipreport-0.1.dist-info/top_level.txt
zipreport-0.1.dist-info/RECORD
