Metadata-Version: 2.1
Name: zipreport
Version: 0.1
Summary: Very lightweight PDF report generation
Home-page: https://github.com/iluvcapra/zipreport
Author: Jamie Hardt
License: MIT
Project-URL: Source, https://github.com/iluvcapra/zipreport
Project-URL: Issues, https://github.com/iluvcapra/zipreport/issues
Keywords: reports pdf cairo pango
Platform: UNKNOWN
Classifier: License :: OSI Approved :: MIT License
Classifier: Programming Language :: Python :: 3.7
Classifier: Development Status :: 4 - Beta
Classifier: Environment :: Console
Classifier: Topic :: Printing
Classifier: Topic :: Office/Business
Requires-Dist: pangocffi
Requires-Dist: cairocffi
Requires-Dist: pangocairocffi
